{
	"msg_login" : "כניסה",
	"msg_logout" : "יציאה",
	"msg_search" : "חיפוש מוצר לפי שם או מותג:",
	"msg_search_button" : "חיפוש",
	"msg_scan_product" : "יש לסרוק את הברקוד כדי לחפש או להוסיף מוצר:",
	"msg_scan" : "סריקה",
	"msg_description" : "<img src=\"openfoodfacts-logo-he.png\" alt=\"Open Food Facts\" /><br /><p>Open Food Facts אוסף מידע ונתונים על מוצרי מזון מרחבי העולם במסד נתונים חופשי ופתוח.</p>",
	"msg_back" : "חזרה",
	"msg_close" : "סגירה",
	"msg_please_login" : "יש להיכנס כדי להוסיף מוצרים או לערוך עמודי מוצרים.",
	"msg_userid" : "שם משתמש או כתובת דוא״ל:",
	"msg_password" : "ססמה:",
	"msg_register" : "אין לך חשבון עדיין? <a href=\"http://world-he.openfoodfacts.org/cgi/user.pl\" target=\"_blank\">יצירת חשבון</a>",
	"msg_language" : "שפה מועדפת:",
	"msg_language_info" : "חיפוש יחזיר את המוצרים בעדיפות גבוהה בשפה הנבחרה, ומוצרים שיתווספו על ידיך יתווספו אל הגרסה התואמת של Open Food Facts.",
	"msg_parameters" : "משתנים",
	"msg_hello" : "שלום $1!",
	"msg_uploading" : "מתבצעת שליחה",
	"msg_uploaded" : "התמונה התקבלה, תודה!",
	"msg_upload_problem" : "לא ניתן לשלוח את התמונה",
	"msg_upload_retry" : "ניסיון חוזר",
	"msg_search_in_progress" : "החיפוש מתבצע",
	"msg_connecting" : "מתבצעת התחברות",
	"msg_connecting_failed" : "ההתחברות נכשלה: אין רשת?",
	"msg_connecting_bad_password" : "שם המשתמש או הססמה שגויים",
	"msg_loading_product" : "מוצר ממסד הנתונים של Open Food Facts נטען",
	"msg_product_title" : "מוצר $1",
	"msg_add_product_without_barcode" : "הוספת מוצר ללא ברקוד",
	"msg_barcode" : "ברקוד: $1"
}
