{
	"msg_login" : "Σύνδεση",
	"msg_logout" : "Αποσύνδεση",
	"msg_search" : "Αναζήτηση προϊόντος με όνομα ή μάρκα:",
	"msg_search_button" : "Αναζήτηση",
	"msg_scan_product" : "Σαρώστε το barcode για να βρείτε ή να προσθέσετε ένα προϊόν:",
	"msg_scan" : "Σάρωση",
	"msg_description" : "<img src=\"openfoodfacts-logo-el.png\" alt=\"Open Food Facts\" /><br /><p>Το Open Food Facts συλλέγει πληροφορίες και δεδομένα για προϊόντα διατροφής από όλο τον κόσμο σε μια ελεύθερη και ανοικτή βάση δεδομένων.</p>",
	"msg_back" : "Πίσω",
	"msg_close" : "Κλείσιμο",
	"msg_please_login" : "Συνδεθείτε για να προσθέσετε προϊόντα ή να επεξεργαστείτε σελίδες προϊόντων.",
	"msg_userid" : "Όνομα χρήστη ή διεύθυνση email:",
	"msg_password" : "Κωδικός:",
	"msg_register" : "Δεν έχετε λογαριασμό; <a href=\"https://world-el.openfoodfacts.org/cgi/user.pl\" target=\"_blank\">Δημιουργία λογαριασμού</a>",
	"msg_language" : "Προτιμώμενη γλώσσα:",
	"msg_language_info" : "Η αναζήτηση θα επιστρέφει με σειρά προτεραιότητας τα προϊόντα της επιλεγμένης γλώσσας, ενώ τα προϊόντα που προσθέτετε θα συμπεριληφθούν στην αντίστοιχη έκδοση του Open Food Facts.",
	"msg_parameters" : "Παράμετροι",
	"msg_hello" : "Γεια σας $1!",
	"msg_uploading" : "Αποστολή σε εξέλιξη",
	"msg_uploaded" : "Η εικόνα ελήφθη, ευχαριστούμε!",
	"msg_upload_problem" : "Αδυναμία αποστολής εικόνας",
	"msg_upload_retry" : "Προσπαθήστε ξανά",
	"msg_search_in_progress" : "Αναζήτηση σε εξέλιξη",
	"msg_connecting" : "Γίνεται σύνδεση",
	"msg_connecting_failed" : "Αποτυχία σύνδεσης: μήπως δεν υπάρχει δίκτυο;",
	"msg_connecting_bad_password" : "Εσφαλμένο όνομα χρήστη ή κωδικός",
	"msg_loading_product" : "Γίνεται φόρτωση προϊόντος από τη βάση δεδομένων του Open Food Facts",
	"msg_product_title" : "Προϊόν $1",
	"msg_add_product_without_barcode" : "Προσθήκη προϊόντος χωρίς barcode",
	"msg_barcode" : "Barcode: $1"
}
